gym/__init__.py
gym/core.py
gym/error.py
gym/logger.py
gym/version.py
gym/envs/__init__.py
gym/envs/registration.py
gym/envs/box2d/__init__.py
gym/envs/box2d/bipedal_walker.py
gym/envs/box2d/car_dynamics.py
gym/envs/box2d/car_racing.py
gym/envs/box2d/lunar_lander.py
gym/envs/classic_control/__init__.py
gym/envs/classic_control/acrobot.py
gym/envs/classic_control/cartpole.py
gym/envs/classic_control/continuous_mountain_car.py
gym/envs/classic_control/mountain_car.py
gym/envs/classic_control/pendulum.py
gym/envs/classic_control/rendering.py
gym/envs/classic_control/assets/clockwise.png
gym/envs/mujoco/__init__.py
gym/envs/mujoco/ant.py
gym/envs/mujoco/ant_v3.py
gym/envs/mujoco/half_cheetah.py
gym/envs/mujoco/half_cheetah_v3.py
gym/envs/mujoco/hopper.py
gym/envs/mujoco/hopper_v3.py
gym/envs/mujoco/humanoid.py
gym/envs/mujoco/humanoid_v3.py
gym/envs/mujoco/humanoidstandup.py
gym/envs/mujoco/inverted_double_pendulum.py
gym/envs/mujoco/inverted_pendulum.py
gym/envs/mujoco/mujoco_env.py
gym/envs/mujoco/pusher.py
gym/envs/mujoco/reacher.py
gym/envs/mujoco/striker.py
gym/envs/mujoco/swimmer.py
gym/envs/mujoco/swimmer_v3.py
gym/envs/mujoco/thrower.py
gym/envs/mujoco/walker2d.py
gym/envs/mujoco/walker2d_v3.py
gym/envs/mujoco/assets/ant.xml
gym/envs/mujoco/assets/half_cheetah.xml
gym/envs/mujoco/assets/hopper.xml
gym/envs/mujoco/assets/humanoid.xml
gym/envs/mujoco/assets/humanoidstandup.xml
gym/envs/mujoco/assets/inverted_double_pendulum.xml
gym/envs/mujoco/assets/inverted_pendulum.xml
gym/envs/mujoco/assets/point.xml
gym/envs/mujoco/assets/pusher.xml
gym/envs/mujoco/assets/reacher.xml
gym/envs/mujoco/assets/striker.xml
gym/envs/mujoco/assets/swimmer.xml
gym/envs/mujoco/assets/thrower.xml
gym/envs/mujoco/assets/walker2d.xml
gym/envs/robotics/__init__.py
gym/envs/robotics/fetch_env.py
gym/envs/robotics/hand_env.py
gym/envs/robotics/robot_env.py
gym/envs/robotics/rotations.py
gym/envs/robotics/utils.py
gym/envs/robotics/assets/LICENSE.md
fragile_gym-1.21.1.dist-info/LICENSE.md
fragile_gym-1.21.1.dist-info/METADATA
fragile_gym-1.21.1.dist-info/WHEEL
fragile_gym-1.21.1.dist-info/top_level.txt
fragile_gym-1.21.1.dist-info/RECORD
