Metadata-Version: 2.1
Name: fragile-gym
Version: 1.21.1
Summary: Gym: A universal API for reinforcement learning environments.
Author-email: OpenAI <jkterry@umd.edu>
Project-URL: Homepage, https://github.com/openai/gym
Classifier: Programming Language :: Python :: 3
Classifier: Programming Language :: Python :: 3.6
Classifier: Programming Language :: Python :: 3.7
Classifier: Programming Language :: Python :: 3.8
Classifier: Programming Language :: Python :: 3.9
Requires-Python: >=3.6
License-File: LICENSE.md
Requires-Dist: numpy>=1.18.0
Requires-Dist: cloudpickle>=1.2.0
Requires-Dist: ipython>=8.27.0
Requires-Dist: importlib-metadata>=4.8.1; python_version <= "3.8"
Provides-Extra: accept-rom-license
Requires-Dist: autorom[accept-rom-license]==0.4.2; extra == "accept-rom-license"
Provides-Extra: atari
Requires-Dist: ale-py==0.7.1; extra == "atari"
Provides-Extra: box2d
Requires-Dist: box2d-py==2.3.5; extra == "box2d"
Requires-Dist: pyglet>=1.4.0; extra == "box2d"
